[
  {
    "item_id": "9475914",
    "amount": "20700",
    "currency": "USD",
    "Şəhər": "Bakı",
    "Marka": "Changan",
    "Model": "Uni-Z",
    "Buraxılış ili": "2025",
    "Ban növü": "Offroader / SUV, 5 qapı",
    "Rəng": "Boz",
    "Mühərrik": "1.5 L / 215 a.g. / Plug-in Hibrid",
    "Yürüş": "0 km"
  },
  {
    "item_id": "9484809",
    "amount": "17400",
    "currency": "AZN",
    "Şəhər": "Bakı",
    "Marka": "Ford",
    "Model": "Fusion (North America)",
    "Buraxılış ili": "2016",
    "Ban növü": "Sedan",
    "Rəng": "Göy",
    "Mühərrik": "1.5 L / 181 a.g. / Benzin",
    "Yürüş": "223 699 km"
  },
  {
    "item_id": "8962955",
    "amount": "19500",
    "currency": "AZN",
    "Şəhər": "Bakı",
    "Marka": "Volkswagen",
    "Model": "Scirocco",
    "Buraxılış ili": "2010",
    "Ban növü": "Hetçbek, 3 qapı",
    "Rəng": "Qara",
    "Mühərrik": "1.4 L / 160 a.g. / Benzin",
    "Yürüş": "204 000 km"
  },
  {
    "item_id": "9479629",
    "amount": "31500",
    "currency": "USD",
    "Şəhər": "Bakı",
    "Marka": "Changan",
    "Model": "Deepal S09",
    "Buraxılış ili": "2025",
    "Ban növü": "Offroader / SUV, 5 qapı",
    "Rəng": "Göy",
    "Mühərrik": "1.5 L / 318 a.g. / Plug-in Hibrid",
    "Yürüş": "0 km"
  },
  {
    "item_id": "9477675",
    "amount": "17700",
    "currency": "AZN",
    "Şəhər": "Sumqayıt",
    "Marka": "Ford",
    "Model": "Kuga",
    "Buraxılış ili": "2013",
    "Ban növü": "Offroader / SUV, 5 qapı",
    "Rəng": "Ağ",
    "Mühərrik": "1.6 L / 150 a.g. / Benzin",
    "Yürüş": "258 470 km"
  },
  {
    "item_id": "9459989",
    "amount": "27500",
    "currency": "AZN",
    "Şəhər": "Sumqayıt",
    "Marka": "Kia",
    "Model": "Sportage",
    "Buraxılış ili": "2014",
    "Ban növü": "Offroader / SUV, 5 qapı",
    "Rəng": "Ağ",
    "Mühərrik": "2.0 L / 184 a.g. / Dizel",
    "Yürüş": "203 870 km"
  },
  {
    "item_id": "9483665",
    "amount": "37000",
    "currency": "AZN",
    "Şəhər": "Bakı",
    "Marka": "Toyota",
    "Model": "Yaris Cross",
    "Buraxılış ili": "2023",
    "Ban növü": "Offroader / SUV, 5 qapı",
    "Rəng": "Qızılı",
    "Mühərrik": "1.5 L / 120 a.g. / Benzin",
    "Yürüş": "20 000 km"
  },
  {
    "item_id": "9410138",
    "amount": "21900",
    "currency": "AZN",
    "Şəhər": "Bakı",
    "Marka": "Hyundai",
    "Model": "Elantra",
    "Buraxılış ili": "2018",
    "Ban növü": "Sedan",
    "Rəng": "Qara",
    "Mühərrik": "2.0 L / 150 a.g. / Benzin",
    "Yürüş": "108 000 km"
  },
  {
    "item_id": "9437839",
    "amount": "22900",
    "currency": "AZN",
    "Şəhər": "Bakı",
    "Marka": "Hyundai",
    "Model": "Elantra",
    "Buraxılış ili": "2018",
    "Ban növü": "Sedan",
    "Rəng": "Qara",
    "Mühərrik": "2.0 L / 200 a.g. / Benzin",
    "Yürüş": "167 000 km"
  },
  {
    "item_id": "9514140",
    "amount": "54000",
    "currency": "AZN",
    "Şəhər": "Bakı",
    "Marka": "Scania",
    "Model": "R420",
    "Buraxılış ili": "2012",
    "Ban növü": "Dartqı",
    "Rəng": "Ağ",
    "Mühərrik": "12 L / 420 a.g. / Dizel",
    "Yürüş": "1 098 000 km"
  },
  {
    "item_id": "9514137",
    "amount": "11500",
    "currency": "AZN",
    "Şəhər": "Göyçay",
    "Marka": "BMW",
    "Model": "530",
    "Buraxılış ili": "2002",
    "Ban növü": "Sedan",
    "Rəng": "Ağ",
    "Mühərrik": "3.0 L / 231 a.g. / Benzin",
    "Yürüş": "250 000 km"
  },
  {
    "item_id": "9513319",
    "amount": "14000",
    "currency": "AZN",
    "Şəhər": "Bakı",
    "Marka": "Nissan",
    "Model": "Note",
    "Buraxılış ili": "2016",
    "Ban növü": "Hetçbek, 5 qapı",
    "Rəng": "Ağ",
    "Mühərrik": "1.2 L / 98 a.g. / Benzin",
    "Yürüş": "80 586 km"
  },
  {
    "item_id": "9055483",
    "amount": "39500",
    "currency": "USD",
    "Şəhər": "Bakı",
    "Marka": "Mercedes",
    "Model": "CLA 200",
    "Buraxılış ili": "2019",
    "Ban növü": "Sedan",
    "Rəng": "Ağ",
    "Mühərrik": "1.4 L / 163 a.g. / Benzin",
    "Yürüş": "26 000 km"
  },
  {
    "item_id": "8977140",
    "amount": "36500",
    "currency": "USD",
    "Şəhər": "Bakı",
    "Marka": "Lexus",
    "Model": "LX 570",
    "Buraxılış ili": "2012",
    "Ban növü": "Offroader / SUV, 5 qapı",
    "Rəng": "Ağ",
    "Mühərrik": "5.7 L / 383 a.g. / Benzin",
    "Yürüş": "170 000 km"
  },
  {
    "item_id": "9403912",
    "amount": "18900",
    "currency": "AZN",
    "Şəhər": "Bakı",
    "Marka": "Toyota",
    "Model": "Camry",
    "Buraxılış ili": "2010",
    "Ban növü": "Sedan",
    "Rəng": "Qara",
    "Mühərrik": "2.5 L / 179 a.g. / Benzin",
    "Yürüş": "197 000 km"
  },
  {
    "item_id": "9316501",
    "amount": "12600",
    "currency": "AZN",
    "Şəhər": "Sumqayıt",
    "Marka": "Chevrolet",
    "Model": "Cruze",
    "Buraxılış ili": "2013",
    "Ban növü": "Sedan",
    "Rəng": "Ağ",
    "Mühərrik": "1.4 L / 140 a.g. / Benzin",
    "Yürüş": "221 000 km"
  },
  {
    "item_id": "9480119",
    "amount": "24800",
    "currency": "AZN",
    "Şəhər": "Sumqayıt",
    "Marka": "Nissan",
    "Model": "Pathfinder",
    "Buraxılış ili": "2012",
    "Ban növü": "Offroader / SUV, 5 qapı",
    "Rəng": "Qara",
    "Mühərrik": "3.5 L / 249 a.g. / Benzin",
    "Yürüş": "281 915 km"
  },
  {
    "item_id": "9442779",
    "amount": "44700",
    "currency": "AZN",
    "Şəhər": "Gəncə",
    "Marka": "Toyota",
    "Model": "Land Cruiser Prado",
    "Buraxılış ili": "2013",
    "Ban növü": "Offroader / SUV, 5 qapı",
    "Rəng": "Ağ",
    "Mühərrik": "2.7 L / 163 a.g. / Benzin",
    "Yürüş": "53 000 km"
  },
  {
    "item_id": "9493572",
    "amount": "24500",
    "currency": "AZN",
    "Şəhər": "Sumqayıt",
    "Marka": "Hyundai",
    "Model": "ix35",
    "Buraxılış ili": "2014",
    "Ban növü": "Offroader / SUV, 5 qapı",
    "Rəng": "Ağ",
    "Mühərrik": "2.4 L / 178 a.g. / Benzin",
    "Yürüş": "252 080 km"
  },
  {
    "item_id": "9495617",
    "amount": "18300",
    "currency": "AZN",
    "Şəhər": "Bakı",
    "Marka": "Hyundai",
    "Model": "Elantra",
    "Buraxılış ili": "2012",
    "Ban növü": "Sedan",
    "Rəng": "Boz",
    "Mühərrik": "1.8 L / 150 a.g. / Benzin",
    "Yürüş": "180 000 km"
  },
  {
    "item_id": "9315607",
    "amount": "32500",
    "currency": "AZN",
    "Şəhər": "Bakı",
    "Marka": "Kia",
    "Model": "Sorento",
    "Buraxılış ili": "2015",
    "Ban növü": "Offroader / SUV, 5 qapı",
    "Rəng": "Ağ",
    "Mühərrik": "2.0 L / 184 a.g. / Dizel",
    "Yürüş": "212 001 km"
  },
  {
    "item_id": "9478943",
    "amount": "21500",
    "currency": "AZN",
    "Şəhər": "Sumqayıt",
    "Marka": "Hyundai",
    "Model": "Avante",
    "Buraxılış ili": "2015",
    "Ban növü": "Sedan",
    "Rəng": "Göy",
    "Mühərrik": "1.6 L / 136 a.g. / Dizel",
    "Yürüş": "176 214 km"
  },
  {
    "item_id": "9467401",
    "amount": "9500",
    "currency": "AZN",
    "Şəhər": "Bakı",
    "Marka": "Hyundai",
    "Model": "Getz",
    "Buraxılış ili": "2007",
    "Ban növü": "Hetçbek, 5 qapı",
    "Rəng": "Qəhvəyi",
    "Mühərrik": "1.4 L / 97 a.g. / Benzin",
    "Yürüş": "216 000 km"
  },
  {
    "item_id": "9514138",
    "amount": "22500",
    "currency": "AZN",
    "Şəhər": "Bakı",
    "Marka": "BMW",
    "Model": "328",
    "Buraxılış ili": "2013",
    "Ban növü": "Sedan",
    "Rəng": "Qara",
    "Mühərrik": "2.0 L / 245 a.g. / Benzin",
    "Yürüş": "230 000 km"
  },
  {
    "item_id": "9474846",
    "amount": "30500",
    "currency": "AZN",
    "Şəhər": "Bakı",
    "Marka": "Hyundai",
    "Model": "Santa Fe",
    "Buraxılış ili": "2017",
    "Ban növü": "Offroader / SUV, 5 qapı",
    "Rəng": "Mavi",
    "Mühərrik": "2.0 L / 240 a.g. / Benzin",
    "Yürüş": "68 500 km"
  },
  {
    "item_id": "9350637",
    "amount": "31600",
    "currency": "AZN",
    "Şəhər": "Bakı",
    "Marka": "Land Rover",
    "Model": "Discovery Sport",
    "Buraxılış ili": "2017",
    "Ban növü": "Offroader / SUV, 5 qapı",
    "Rəng": "Ağ",
    "Mühərrik": "2.0 L / 240 a.g. / Benzin",
    "Yürüş": "125 000 km"
  },
  {
    "item_id": "9497122",
    "amount": "65500",
    "currency": "AZN",
    "Şəhər": "Bakı",
    "Marka": "Mitsubishi",
    "Model": "Pajero Sport",
    "Buraxılış ili": "2023",
    "Ban növü": "Offroader / SUV, 5 qapı",
    "Rəng": "Yaş Asfalt",
    "Mühərrik": "2.4 L / 181 a.g. / Dizel",
    "Yürüş": "63 000 km"
  },
  {
    "item_id": "9315428",
    "amount": "19900",
    "currency": "AZN",
    "Şəhər": "Bakı",
    "Marka": "Chevrolet",
    "Model": "Malibu",
    "Buraxılış ili": "2018",
    "Ban növü": "Sedan",
    "Rəng": "Ağ",
    "Mühərrik": "1.5 L / 160 a.g. / Benzin",
    "Yürüş": "213 000 km"
  },
  {
    "item_id": "9165427",
    "amount": "23500",
    "currency": "USD",
    "Şəhər": "Bakı",
    "Marka": "Chevrolet",
    "Model": "Camaro",
    "Buraxılış ili": "2013",
    "Ban növü": "Kupe",
    "Rəng": "Qara",
    "Mühərrik": "6.2 L / 405 a.g. / Benzin",
    "Yürüş": "181 000 km"
  },
  {
    "item_id": "9304577",
    "amount": "21800",
    "currency": "AZN",
    "Şəhər": "Bakı",
    "Marka": "Hyundai",
    "Model": "Elantra",
    "Buraxılış ili": "2016",
    "Ban növü": "Sedan",
    "Rəng": "Göy",
    "Mühərrik": "2.0 L / 150 a.g. / Benzin",
    "Yürüş": "137 000 km"
  },
  {
    "item_id": "9514142",
    "amount": "8500",
    "currency": "AZN",
    "Şəhər": "Bakı",
    "Marka": "Mazda",
    "Model": "6",
    "Buraxılış ili": "2003",
    "Ban növü": "Sedan",
    "Rəng": "Ağ",
    "Mühərrik": "2.0 L / 145 a.g. / Benzin",
    "Yürüş": "354 765 km"
  },
  {
    "item_id": "9372756",
    "amount": "49900",
    "currency": "USD",
    "Şəhər": "Bakı",
    "Marka": "ZEEKR",
    "Model": "Mix",
    "Buraxılış ili": "2025",
    "Ban növü": "Minivan",
    "Rəng": "Ağ",
    "Mühərrik": "422 a.g. / Elektro",
    "Yürüş": "0 km"
  },
  {
    "item_id": "9427264",
    "amount": "10900",
    "currency": "AZN",
    "Şəhər": "Bakı",
    "Marka": "Ravon",
    "Model": "Nexia R3",
    "Buraxılış ili": "2017",
    "Ban növü": "Sedan",
    "Rəng": "Ağ",
    "Mühərrik": "1.5 L / 107 a.g. / Benzin",
    "Yürüş": "247 200 km"
  },
  {
    "item_id": "9512985",
    "amount": "38500",
    "currency": "USD",
    "Şəhər": "Bakı",
    "Marka": "Toyota",
    "Model": "Avalon",
    "Buraxılış ili": "2025",
    "Ban növü": "Sedan",
    "Rəng": "Qara",
    "Mühərrik": "2.0 L / 197 a.g. / Hibrid",
    "Yürüş": "0 km"
  },
  {
    "item_id": "9204187",
    "amount": "110000",
    "currency": "USD",
    "Şəhər": "Bakı",
    "Marka": "Ford",
    "Model": "F-150",
    "Buraxılış ili": "2021",
    "Ban növü": "Pikap, ikiqat kabin",
    "Rəng": "Boz",
    "Mühərrik": "3.5 L / 375 a.g. / Benzin",
    "Yürüş": "11 650 km"
  },
  {
    "item_id": "8948342",
    "amount": "43900",
    "currency": "USD",
    "Şəhər": "Bakı",
    "Marka": "Land Rover",
    "Model": "Range Rover",
    "Buraxılış ili": "2016",
    "Ban növü": "Offroader / SUV, 5 qapı",
    "Rəng": "Qara",
    "Mühərrik": "3.0 L / 360 a.g. / Benzin",
    "Yürüş": "115 000 km"
  }
]